Metadata-Version: 2.1
Name: ExportWifi
Version: 0.0.4
Summary: Getting Wifi Files of the target
Home-page: 
Author: Fawaz Bashiru
Author-email: fawazbashiru@gmail.com
License: MIT
Keywords: Wifi
Classifier: Development Status :: 6 - Mature
Classifier: Intended Audience :: Education
Classifier: Operating System :: Microsoft :: Windows :: Windows 10
Classifier: License :: OSI Approved :: MIT License
Classifier: Programming Language :: Python :: 3
